<?xml version="1.0" encoding="UTF-8"?>
<objects serializationModel="Studio.02.03.00">
	<object class="Workspace" id="{2fab86e8-0255-45a2-a271-328a33a2112a}">
		<relationship name="masterEventFolder">
			<destination>{251319a5-e1e1-4fff-9a3a-cb0ed539e1bf}</destination>
		</relationship>
		<relationship name="masterTagFolder">
			<destination>{ee7fc0dd-535a-4792-b6b2-a9c854e0d513}</destination>
		</relationship>
		<relationship name="masterEffectPresetFolder">
			<destination>{d3e0245b-cdbd-4e75-8a59-d71cc3fd16f4}</destination>
		</relationship>
		<relationship name="masterParameterPresetFolder">
			<destination>{dfc69aa0-a1ab-43af-8735-ad6ff216a4a5}</destination>
		</relationship>
		<relationship name="masterBankFolder">
			<destination>{f5c08aa3-0bd6-400d-95a1-98bc740b20b5}</destination>
		</relationship>
		<relationship name="masterSandboxFolder">
			<destination>{aa4b8cff-3f4f-457e-be20-7472abe13bd2}</destination>
		</relationship>
		<relationship name="masterAssetFolder">
			<destination>{65049221-749a-4b57-9089-1141970d0ba8}</destination>
		</relationship>
		<relationship name="mixer">
			<destination>{2c1572f1-19b4-4670-a67e-3081263d8e12}</destination>
		</relationship>
		<relationship name="profilerSessionFolder">
			<destination>{5b90d225-9b52-43b2-9d8d-ed249f4c889f}</destination>
		</relationship>
		<relationship name="platforms">
			<destination>{d257ce03-2a3d-49d0-aa83-a139fc4355a4}</destination>
		</relationship>
	</object>
</objects>
